<?xml version='1.0' encoding='UTF-8'?>
<GateDocument version="3">
<!-- The document's features-->

<GateDocumentFeatures>
<Feature>
  <Name className="java.lang.String">MimeType</Name>
  <Value className="java.lang.String">text/plain</Value>
</Feature>
<Feature>
  <Name className="java.lang.String">gate.SourceURL</Name>
  <Value className="java.lang.String">file:/home/adrian/linkedtvtest/subtitles/77.txt</Value>
</Feature>
<Feature>
  <Name className="java.lang.String">docNewLineType</Name>
  <Value className="java.lang.String">LF</Value>
</Feature>
</GateDocumentFeatures>
<!-- The document content area with serialized nodes -->

<TextWithNodes><Node id="0"/>Der Aufzug ging an ein paar Punkten
 vorbei, die wir als neuralgischen
 Ansagen.
 Es blieb ruhig.
 Die Stimmung in <Node id="115"/>Schöneweide<Node id="126"/>
    aber bleibt angespannt.
 Das <Node id="160"/>Antifa-Konzert am Abschlussort<Node id="190"/>
soll bis nach Miternacht andauern.
 Mehr Polizisten als Partygäste,
 so begann die <Node id="274"/>Walpurgisnacht<Node id="288"/>
     im <Node id="297"/>Berliner <Node id="306"/>Mauerpark<Node id="315"/>.
 Das Gelände ist abgesperrt und
die <Node id="353"/>Polizei<Node id="360"/> kontrolliert genau.
 <Node id="382"/>Ulli Zelle<Node id="392"/> ist vor Ort.
 Füllt es sich denn langsam
   und wie ist die Stimmung?
 Mittlerweile ist das
 Verhältnis hier etwas gekippt.
 Es gibt jetzt wieder etwas
mehr Partygäste als Polizisten.
 Ca. 3000 Beamte sind im Einsatz.
 Es wird hier getanzt.
 Ein paar Hexen sind auch dabei.
 Über dem <Node id="677"/>Wedding<Node id="684"/> ist
 es rot, da unten in der <Node id="714"/>Arena
 im <Node id="724"/>Mauerpark<Node id="733"/> hat man sich um
      ein Feuer gesammelt.
 Es wurde dort auch
    eine Suppe warm gemacht.
 Es ist eine schöne Partystimmung.
 Hier gibt es riesige Seifenblasen,
die von Künstlern gemacht werden.
 Über allem wacht das
      Anti-Konflikt-Team.
 Es sind nicht so viele gekommen, das                                
  liegt möglicherweise am Wetter.
 Es gibt aber auch die
      Fußball-Konkurrenz.
 Weit ist das Rückspiel von
<Node id="1160"/>Real Madrid<Node id="1171"/> gegen <Node id="1178"/>Borussia Dortmund<Node id="1195"/>.
 Zehn Jahre ohne Randale
     ist man ausgekommen.
 Die Freunde des <Node id="1265"/>Mauerparks<Node id="1275"/> sind
      sehr froh darüber.
 Wir sind sehr froh darüber,
    dass die Zusammenarbeit
 mit dem Bezirksamt
  unter <Node id="1391"/>Polizei<Node id="1398"/> so gut läuft.
 Viele ehrenamtliche Menschen sind
         hier unterwegs.
 Sie müssen
sich hier Einlasskontrollen gefallen
 lassen, das machen aber viele.
 Die meisten machen das mit,
    es ist eine gute Party.
 Viele verstehen, was hier nötig
ist, um für Sicherheit zu sorgen.
 Es ist Vergangenheit, das am
<Node id="1708"/>Mauerpark<Node id="1717"/> Randale begonnen hat.
 Es gibt noch eine Demonstration
im Wedding, vom Gesundbrunnen.
 Sie begann vor 1 Stunde.
 Sie wurde
von vielen Polizisten begleitet.
 Es geht
gegen Zwangsräumung, Mietsteigerung.
 Viel <Node id="1926"/>Polizei<Node id="1933"/>, wie man sah.
 Von der <Node id="1957"/>Berliner Polizei<Node id="1973"/> habe ich
      jetzt jemanden hier.
 Es sind jetzt 1000 Menschen wir
        demonstrieren.
 Es wurden einige
  Feuerwerkskörper angezündet.
 Bis erstes friedlich.
 In <Node id="2142"/>Schöneweide<Node id="2153"/> blieb es ruhig.
 Es gab dort aber einige Festnahmen.
 Ist der aktuelle Stand?
 Auch dort sind noch 1000 Menschen
         am Ende Platz.
 Es blieb insgesamt störungsfrei.
 Vielen Dank Ihnen beiden.
 <Node id="2353"/></TextWithNodes>
<!-- The default annotation set -->

<AnnotationSet>
</AnnotationSet>

<!-- Named annotation set -->

<AnnotationSet Name="Original markups">
<Annotation Id="0" Type="paragraph" StartNode="0" EndNode="2353">
</Annotation>
</AnnotationSet>

<!-- Named annotation set -->

<AnnotationSet Name="ann-2">
<Annotation Id="32" Type="Mention" StartNode="382" EndNode="392">
<Feature>
  <Name className="java.lang.String">class</Name>
  <Value className="java.lang.String">http://semanticlab.net/ontology/recognyze#Person</Value>
</Feature>
<Feature>
  <Name className="java.lang.String">ontology</Name>
  <Value className="java.lang.String">http://semanticlab.net/ontology/recognyze</Value>
</Feature>
<Feature>
  <Name className="java.lang.String">hasURI</Name>
  <Value className="java.util.ArrayList" itemClassName="java.lang.String">http://de.dbpedia.org/page/Ulli_Zelle</Value>
</Feature>
</Annotation>
<Annotation Id="33" Type="Mention" StartNode="1160" EndNode="1171">
<Feature>
  <Name className="java.lang.String">class</Name>
  <Value className="java.lang.String">http://semanticlab.net/ontology/recognyze#Organisation</Value>
</Feature>
<Feature>
  <Name className="java.lang.String">ontology</Name>
  <Value className="java.lang.String">http://semanticlab.net/ontology/recognyze</Value>
</Feature>
<Feature>
  <Name className="java.lang.String">hasURI</Name>
  <Value className="java.util.ArrayList" itemClassName="java.lang.String">http://de.dbpedia.org/page/Real_Madrid</Value>
</Feature>
</Annotation>
<Annotation Id="34" Type="Mention" StartNode="1178" EndNode="1195">
<Feature>
  <Name className="java.lang.String">class</Name>
  <Value className="java.lang.String">http://semanticlab.net/ontology/recognyze#Organisation</Value>
</Feature>
<Feature>
  <Name className="java.lang.String">ontology</Name>
  <Value className="java.lang.String">http://semanticlab.net/ontology/recognyze</Value>
</Feature>
<Feature>
  <Name className="java.lang.String">hasURI</Name>
  <Value className="java.util.ArrayList" itemClassName="java.lang.String">http://de.dbpedia.org/page/Borussia_Dortmund</Value>
</Feature>
</Annotation>
<Annotation Id="36" Type="Mention" StartNode="306" EndNode="315">
<Feature>
  <Name className="java.lang.String">class</Name>
  <Value className="java.lang.String">http://semanticlab.net/ontology/recognyze#Location</Value>
</Feature>
<Feature>
  <Name className="java.lang.String">ontology</Name>
  <Value className="java.lang.String">http://semanticlab.net/ontology/recognyze</Value>
</Feature>
<Feature>
  <Name className="java.lang.String">hasURI</Name>
  <Value className="java.util.ArrayList" itemClassName="java.lang.String">http://de.dbpedia.org/page/Mauerpark</Value>
</Feature>
</Annotation>
<Annotation Id="37" Type="Mention" StartNode="724" EndNode="733">
<Feature>
  <Name className="java.lang.String">class</Name>
  <Value className="java.lang.String">http://semanticlab.net/ontology/recognyze#Location</Value>
</Feature>
<Feature>
  <Name className="java.lang.String">ontology</Name>
  <Value className="java.lang.String">http://semanticlab.net/ontology/recognyze</Value>
</Feature>
<Feature>
  <Name className="java.lang.String">hasURI</Name>
  <Value className="java.util.ArrayList" itemClassName="java.lang.String">http://de.dbpedia.org/page/Mauerpark</Value>
</Feature>
</Annotation>
<Annotation Id="39" Type="Mention" StartNode="1708" EndNode="1717">
<Feature>
  <Name className="java.lang.String">class</Name>
  <Value className="java.lang.String">http://semanticlab.net/ontology/recognyze#Location</Value>
</Feature>
<Feature>
  <Name className="java.lang.String">ontology</Name>
  <Value className="java.lang.String">http://semanticlab.net/ontology/recognyze</Value>
</Feature>
<Feature>
  <Name className="java.lang.String">hasURI</Name>
  <Value className="java.util.ArrayList" itemClassName="java.lang.String">http://de.dbpedia.org/page/Mauerpark</Value>
</Feature>
</Annotation>
<Annotation Id="40" Type="Mention" StartNode="1265" EndNode="1275">
<Feature>
  <Name className="java.lang.String">class</Name>
  <Value className="java.lang.String">http://semanticlab.net/ontology/recognyze#Location</Value>
</Feature>
<Feature>
  <Name className="java.lang.String">ontology</Name>
  <Value className="java.lang.String">http://semanticlab.net/ontology/recognyze</Value>
</Feature>
<Feature>
  <Name className="java.lang.String">hasURI</Name>
  <Value className="java.util.ArrayList" itemClassName="java.lang.String">http://de.dbpedia.org/page/Mauerpark</Value>
</Feature>
</Annotation>
<Annotation Id="41" Type="Mention" StartNode="677" EndNode="684">
<Feature>
  <Name className="java.lang.String">class</Name>
  <Value className="java.lang.String">http://semanticlab.net/ontology/recognyze#Location</Value>
</Feature>
<Feature>
  <Name className="java.lang.String">ontology</Name>
  <Value className="java.lang.String">http://semanticlab.net/ontology/recognyze</Value>
</Feature>
<Feature>
  <Name className="java.lang.String">hasURI</Name>
  <Value className="java.util.ArrayList" itemClassName="java.lang.String">http://de.dbpedia.org/page/Berlin-Wedding</Value>
</Feature>
</Annotation>
<Annotation Id="42" Type="Mention" StartNode="115" EndNode="126">
<Feature>
  <Name className="java.lang.String">class</Name>
  <Value className="java.lang.String">http://semanticlab.net/ontology/recognyze#Location</Value>
</Feature>
<Feature>
  <Name className="java.lang.String">ontology</Name>
  <Value className="java.lang.String">http://semanticlab.net/ontology/recognyze</Value>
</Feature>
<Feature>
  <Name className="java.lang.String">hasURI</Name>
  <Value className="java.util.ArrayList" itemClassName="java.lang.String">http://de.dbpedia.org/page/Berlin-Sch%C3%B6neweide</Value>
</Feature>
</Annotation>
<Annotation Id="43" Type="Mention" StartNode="2142" EndNode="2153">
<Feature>
  <Name className="java.lang.String">class</Name>
  <Value className="java.lang.String">http://semanticlab.net/ontology/recognyze#Location</Value>
</Feature>
<Feature>
  <Name className="java.lang.String">ontology</Name>
  <Value className="java.lang.String">http://semanticlab.net/ontology/recognyze</Value>
</Feature>
<Feature>
  <Name className="java.lang.String">hasURI</Name>
  <Value className="java.util.ArrayList" itemClassName="java.lang.String">http://de.dbpedia.org/page/Berlin-Sch%C3%B6neweide</Value>
</Feature>
</Annotation>
<Annotation Id="22" Type="Mention" StartNode="160" EndNode="190">
<Feature>
  <Name className="java.lang.String">class</Name>
  <Value className="java.lang.String">http://semanticlab.net/ontology/recognyze#Event</Value>
</Feature>
<Feature>
  <Name className="java.lang.String">ontology</Name>
  <Value className="java.lang.String">http://semanticlab.net/ontology/recognyze</Value>
</Feature>
</Annotation>
<Annotation Id="25" Type="Mention" StartNode="274" EndNode="315">
<Feature>
  <Name className="java.lang.String">class</Name>
  <Value className="java.lang.String">http://semanticlab.net/ontology/recognyze#Event</Value>
</Feature>
<Feature>
  <Name className="java.lang.String">ontology</Name>
  <Value className="java.lang.String">http://semanticlab.net/ontology/recognyze</Value>
</Feature>
</Annotation>
<Annotation Id="26" Type="Mention" StartNode="353" EndNode="360">
<Feature>
  <Name className="java.lang.String">class</Name>
  <Value className="java.lang.String">http://semanticlab.net/ontology/recognyze#Organisation</Value>
</Feature>
<Feature>
  <Name className="java.lang.String">ontology</Name>
  <Value className="java.lang.String">http://semanticlab.net/ontology/recognyze</Value>
</Feature>
<Feature>
  <Name className="java.lang.String">hasURI</Name>
  <Value className="java.util.ArrayList" itemClassName="java.lang.String">http://de.dbpedia.org/page/Polizei</Value>
</Feature>
</Annotation>
<Annotation Id="27" Type="Mention" StartNode="1391" EndNode="1398">
<Feature>
  <Name className="java.lang.String">class</Name>
  <Value className="java.lang.String">http://semanticlab.net/ontology/recognyze#Organisation</Value>
</Feature>
<Feature>
  <Name className="java.lang.String">ontology</Name>
  <Value className="java.lang.String">http://semanticlab.net/ontology/recognyze</Value>
</Feature>
<Feature>
  <Name className="java.lang.String">hasURI</Name>
  <Value className="java.util.ArrayList" itemClassName="java.lang.String">http://de.dbpedia.org/page/Polizei</Value>
</Feature>
</Annotation>
<Annotation Id="28" Type="Mention" StartNode="1926" EndNode="1933">
<Feature>
  <Name className="java.lang.String">class</Name>
  <Value className="java.lang.String">http://semanticlab.net/ontology/recognyze#Organisation</Value>
</Feature>
<Feature>
  <Name className="java.lang.String">ontology</Name>
  <Value className="java.lang.String">http://semanticlab.net/ontology/recognyze</Value>
</Feature>
<Feature>
  <Name className="java.lang.String">hasURI</Name>
  <Value className="java.util.ArrayList" itemClassName="java.lang.String">http://de.dbpedia.org/page/Polizei</Value>
</Feature>
</Annotation>
<Annotation Id="30" Type="Mention" StartNode="1957" EndNode="1973">
<Feature>
  <Name className="java.lang.String">class</Name>
  <Value className="java.lang.String">http://semanticlab.net/ontology/recognyze#Organisation</Value>
</Feature>
<Feature>
  <Name className="java.lang.String">ontology</Name>
  <Value className="java.lang.String">http://semanticlab.net/ontology/recognyze</Value>
</Feature>
</Annotation>
<Annotation Id="31" Type="Mention" StartNode="714" EndNode="733">
<Feature>
  <Name className="java.lang.String">class</Name>
  <Value className="java.lang.String">http://semanticlab.net/ontology/recognyze#Location</Value>
</Feature>
<Feature>
  <Name className="java.lang.String">ontology</Name>
  <Value className="java.lang.String">http://semanticlab.net/ontology/recognyze</Value>
</Feature>
</Annotation>
</AnnotationSet>

<!-- Named annotation set -->

<AnnotationSet Name="ann-1">
<Annotation Id="2" Type="Mention" StartNode="115" EndNode="126">
<Feature>
  <Name className="java.lang.String">class</Name>
  <Value className="java.lang.String">http://semanticlab.net/ontology/recognyze#Location</Value>
</Feature>
<Feature>
  <Name className="java.lang.String">ontology</Name>
  <Value className="java.lang.String">http://semanticlab.net/ontology/recognyze</Value>
</Feature>
<Feature>
  <Name className="java.lang.String">hasURI</Name>
  <Value className="java.util.ArrayList" itemClassName="java.lang.String">http://de.dbpedia.org/page/Berlin-Sch%C3%B6neweide</Value>
</Feature>
</Annotation>
<Annotation Id="3" Type="Mention" StartNode="2142" EndNode="2153">
<Feature>
  <Name className="java.lang.String">class</Name>
  <Value className="java.lang.String">http://semanticlab.net/ontology/recognyze#Location</Value>
</Feature>
<Feature>
  <Name className="java.lang.String">ontology</Name>
  <Value className="java.lang.String">http://semanticlab.net/ontology/recognyze</Value>
</Feature>
<Feature>
  <Name className="java.lang.String">hasURI</Name>
  <Value className="java.util.ArrayList" itemClassName="java.lang.String">http://de.dbpedia.org/page/Berlin-Sch%C3%B6neweide</Value>
</Feature>
</Annotation>
<Annotation Id="4" Type="Mention" StartNode="160" EndNode="190">
<Feature>
  <Name className="java.lang.String">class</Name>
  <Value className="java.lang.String">http://semanticlab.net/ontology/recognyze#Event</Value>
</Feature>
<Feature>
  <Name className="java.lang.String">ontology</Name>
  <Value className="java.lang.String">http://semanticlab.net/ontology/recognyze</Value>
</Feature>
</Annotation>
<Annotation Id="6" Type="Mention" StartNode="274" EndNode="288">
<Feature>
  <Name className="java.lang.String">class</Name>
  <Value className="java.lang.String">http://semanticlab.net/ontology/recognyze#Event</Value>
</Feature>
<Feature>
  <Name className="java.lang.String">ontology</Name>
  <Value className="java.lang.String">http://semanticlab.net/ontology/recognyze</Value>
</Feature>
</Annotation>
<Annotation Id="7" Type="Mention" StartNode="297" EndNode="315">
<Feature>
  <Name className="java.lang.String">class</Name>
  <Value className="java.lang.String">http://semanticlab.net/ontology/recognyze#Location</Value>
</Feature>
<Feature>
  <Name className="java.lang.String">ontology</Name>
  <Value className="java.lang.String">http://semanticlab.net/ontology/recognyze</Value>
</Feature>
<Feature>
  <Name className="java.lang.String">hasURI</Name>
  <Value className="java.util.ArrayList" itemClassName="java.lang.String">http://de.dbpedia.org/page/Mauerpark</Value>
</Feature>
</Annotation>
<Annotation Id="8" Type="Mention" StartNode="382" EndNode="392">
<Feature>
  <Name className="java.lang.String">class</Name>
  <Value className="java.lang.String">http://semanticlab.net/ontology/recognyze#Person</Value>
</Feature>
<Feature>
  <Name className="java.lang.String">ontology</Name>
  <Value className="java.lang.String">http://semanticlab.net/ontology/recognyze</Value>
</Feature>
<Feature>
  <Name className="java.lang.String">hasURI</Name>
  <Value className="java.util.ArrayList" itemClassName="java.lang.String">http://de.dbpedia.org/page/Ulli_Zelle</Value>
</Feature>
</Annotation>
<Annotation Id="9" Type="Mention" StartNode="353" EndNode="360">
<Feature>
  <Name className="java.lang.String">class</Name>
  <Value className="java.lang.String">http://semanticlab.net/ontology/recognyze#Organisation</Value>
</Feature>
<Feature>
  <Name className="java.lang.String">ontology</Name>
  <Value className="java.lang.String">http://semanticlab.net/ontology/recognyze</Value>
</Feature>
<Feature>
  <Name className="java.lang.String">hasURI</Name>
  <Value className="java.util.ArrayList" itemClassName="java.lang.String">http://de.dbpedia.org/page/Polizei</Value>
</Feature>
</Annotation>
<Annotation Id="10" Type="Mention" StartNode="1391" EndNode="1398">
<Feature>
  <Name className="java.lang.String">class</Name>
  <Value className="java.lang.String">http://semanticlab.net/ontology/recognyze#Organisation</Value>
</Feature>
<Feature>
  <Name className="java.lang.String">ontology</Name>
  <Value className="java.lang.String">http://semanticlab.net/ontology/recognyze</Value>
</Feature>
<Feature>
  <Name className="java.lang.String">hasURI</Name>
  <Value className="java.util.ArrayList" itemClassName="java.lang.String">http://de.dbpedia.org/page/Polizei</Value>
</Feature>
</Annotation>
<Annotation Id="11" Type="Mention" StartNode="1926" EndNode="1933">
<Feature>
  <Name className="java.lang.String">class</Name>
  <Value className="java.lang.String">http://semanticlab.net/ontology/recognyze#Organisation</Value>
</Feature>
<Feature>
  <Name className="java.lang.String">ontology</Name>
  <Value className="java.lang.String">http://semanticlab.net/ontology/recognyze</Value>
</Feature>
<Feature>
  <Name className="java.lang.String">hasURI</Name>
  <Value className="java.util.ArrayList" itemClassName="java.lang.String">http://de.dbpedia.org/page/Polizei</Value>
</Feature>
</Annotation>
<Annotation Id="14" Type="Mention" StartNode="724" EndNode="733">
<Feature>
  <Name className="java.lang.String">class</Name>
  <Value className="java.lang.String">http://semanticlab.net/ontology/recognyze#Location</Value>
</Feature>
<Feature>
  <Name className="java.lang.String">ontology</Name>
  <Value className="java.lang.String">http://semanticlab.net/ontology/recognyze</Value>
</Feature>
</Annotation>
<Annotation Id="16" Type="Mention" StartNode="1708" EndNode="1717">
<Feature>
  <Name className="java.lang.String">class</Name>
  <Value className="java.lang.String">http://semanticlab.net/ontology/recognyze#Location</Value>
</Feature>
<Feature>
  <Name className="java.lang.String">ontology</Name>
  <Value className="java.lang.String">http://semanticlab.net/ontology/recognyze</Value>
</Feature>
</Annotation>
<Annotation Id="17" Type="Mention" StartNode="1160" EndNode="1171">
<Feature>
  <Name className="java.lang.String">class</Name>
  <Value className="java.lang.String">http://semanticlab.net/ontology/recognyze#Organisation</Value>
</Feature>
<Feature>
  <Name className="java.lang.String">ontology</Name>
  <Value className="java.lang.String">http://semanticlab.net/ontology/recognyze</Value>
</Feature>
<Feature>
  <Name className="java.lang.String">hasURI</Name>
  <Value className="java.util.ArrayList" itemClassName="java.lang.String">http://de.dbpedia.org/page/Real_Madrid</Value>
</Feature>
</Annotation>
<Annotation Id="18" Type="Mention" StartNode="1178" EndNode="1195">
<Feature>
  <Name className="java.lang.String">class</Name>
  <Value className="java.lang.String">http://semanticlab.net/ontology/recognyze#Organisation</Value>
</Feature>
<Feature>
  <Name className="java.lang.String">ontology</Name>
  <Value className="java.lang.String">http://semanticlab.net/ontology/recognyze</Value>
</Feature>
<Feature>
  <Name className="java.lang.String">hasURI</Name>
  <Value className="java.util.ArrayList" itemClassName="java.lang.String">http://de.dbpedia.org/page/Borussia_Dortmund</Value>
</Feature>
</Annotation>
<Annotation Id="19" Type="Mention" StartNode="677" EndNode="684">
<Feature>
  <Name className="java.lang.String">class</Name>
  <Value className="java.lang.String">http://semanticlab.net/ontology/recognyze#Location</Value>
</Feature>
<Feature>
  <Name className="java.lang.String">ontology</Name>
  <Value className="java.lang.String">http://semanticlab.net/ontology/recognyze</Value>
</Feature>
<Feature>
  <Name className="java.lang.String">hasURI</Name>
  <Value className="java.util.ArrayList" itemClassName="java.lang.String">http://de.dbpedia.org/page/Berlin-Wedding</Value>
</Feature>
</Annotation>
<Annotation Id="20" Type="Mention" StartNode="1265" EndNode="1275">
<Feature>
  <Name className="java.lang.String">class</Name>
  <Value className="java.lang.String">http://semanticlab.net/ontology/recognyze#Location</Value>
</Feature>
<Feature>
  <Name className="java.lang.String">ontology</Name>
  <Value className="java.lang.String">http://semanticlab.net/ontology/recognyze</Value>
</Feature>
</Annotation>
<Annotation Id="21" Type="Mention" StartNode="1957" EndNode="1973">
<Feature>
  <Name className="java.lang.String">class</Name>
  <Value className="java.lang.String">http://semanticlab.net/ontology/recognyze#Organisation</Value>
</Feature>
<Feature>
  <Name className="java.lang.String">ontology</Name>
  <Value className="java.lang.String">http://semanticlab.net/ontology/recognyze</Value>
</Feature>
</Annotation>
</AnnotationSet>

</GateDocument>
